vehicle_gui/__init__.py
vehicle_gui/__main__.py
vehicle_gui/_run_vcl.py
vehicle_gui/code_editor.py
vehicle_gui/main_widget.py
vehicle_gui/util.py
vehicle_gui/vcl_bindings.py
vehicle_gui/vcl_utils.py
vehicle_gui/counter_example_view/base_renderer.py
vehicle_gui/counter_example_view/counter_example_tab.py
vehicle_gui/counter_example_view/extract_renderers.py
vehicle_gui/external/lexer.py
vehicle_gui/external/vse_style.py
vehicle_gui/query_view/base_types.py
vehicle_gui/query_view/query_tab.py
vehicle_gui/query_view/graphics/block_graphics.py
vehicle_gui/query_view/graphics/edge_graphics.py
vehicle_gui/query_view/graphics/graphics_scene.py
vehicle_gui/query_view/graphics/graphics_view.py
vehicle_gui/query_view/graphics/socket_graphics.py
vehicle_gui/query_view/styling/__init__.py
vehicle_gui/query_view/styling/dimension.py
vehicle_gui/query_view/styling/palette.py
vehicle_gui/query_view/verification/__init__.py
vehicle_gui/query_view/verification/blocks.py
vehicle_gui/query_view/verification/workflow.py
vehicle_gui/resource_view/input_view.py
vehicle_gui/resource_view/property_view.py
vehicle_gui-0.3.1.dist-info/licenses/LICENSE
vehicle_gui-0.3.1.dist-info/METADATA
vehicle_gui-0.3.1.dist-info/WHEEL
vehicle_gui-0.3.1.dist-info/entry_points.txt
vehicle_gui-0.3.1.dist-info/top_level.txt
vehicle_gui-0.3.1.dist-info/RECORD
