Metadata-Version: 2.4
Name: vehicle_gui
Version: 0.3.1
Summary: A GUI frontend for the vehicle command line tool
Requires-Python: >=3.8
License-File: LICENSE
Requires-Dist: PyQt6>=6.7.0
Requires-Dist: vehicle_lang>=0.21.0
Requires-Dist: superqt>=0.7.0
Requires-Dist: idx2numpy>=1.2.0
Requires-Dist: Pygments>=2.18.0
Dynamic: license-file
